MeetingAssistant/__init__.py
MeetingAssistant/app.py
MeetingAssistant/assistantbot.py
MeetingAssistant/embed.py
MeetingAssistant/gui_launcher.py
MeetingAssistant/query_parser.py
MeetingAssistant/record.py
MeetingAssistant/scheduler.py
MeetingAssistant/search.py
MeetingAssistant/summarize.py
MeetingAssistant/transcribe.py
MeetingAssistant/webhook_listener.py
MeetingAssistant-0.1.1.dist-info/METADATA
MeetingAssistant-0.1.1.dist-info/WHEEL
MeetingAssistant-0.1.1.dist-info/top_level.txt
MeetingAssistant-0.1.1.dist-info/RECORD
