Metadata-Version: 2.1
Name: MeetingAssistant
Version: 0.1.1
Summary: A conversational meeting assistant
Home-page: https://github.com/samruddhitiwari/MeetingAssistant
Author: Samruddhi Tiwari
Author-email: samruddhitiwari003@gmail.com
Classifier: Programming Language :: Python :: 3
Classifier: License :: OSI Approved :: MIT License
Classifier: Operating System :: OS Independent
Requires-Python: >=3.6
Requires-Dist: PySimpleGUI
Requires-Dist: openai
Requires-Dist: faiss-cpu
Requires-Dist: python-telegram-bot
Requires-Dist: python-dotenv
Requires-Dist: sentence-transformers
Requires-Dist: scikit-learn
Requires-Dist: torch
Requires-Dist: tqdm
